<?xml version="1.0" encoding="UTF-8"?>
<tt xmlns="http://www.w3.org/2006/04/ttaf1" xmlns:tts="http://www.w3.org/2006/04/ttaf1#styling" xml:lang="fr">  
<head>
    <styling>
      <style id="defaultCaption" tts:fontSize="16" tts:fontFamily="SansSerif" tts:fontWeight="normal" tts:fontStyle="normal" tts:textDecoration="none" tts:color="yellow" tts:backgroundColor="black" tts:textAlign="center" />
    </styling>
  </head>
<body STYLE="defaultCaption">
       <div begin="0.2s" dur="3.10s"><p><![CDATA[<font size="16">Je travaille avec des équipes de projet dispersées aux quatre coins du pays </font></p></div>
      <div begin="3.30s" dur="3.0s"><p><![CDATA[<font size="16">et de la région de la capitale nationale.</font></p></div>
       <div begin="5.35s" dur="6.50s"><p><![CDATA[<font size="16">Grâce à GCDOCS, il est bien plus facile pour les membres des équipes de partager des fichiers et de demeurer en contact.</font></p></div>
      <div begin="11.20s" dur="4.40s"><p><![CDATA[<font size="16">Plus important encore, il nous aide à toujours être sur la même longueur d’onde.</font></p></div>
	   <div begin="15.20s" dur="4.20s"><p><![CDATA[<font size="16">GCDOCS assure la synchronisation constante de nos fichiers partagés.</font></p></div>
	   <div begin="19.30s" dur="5.0s"><p><![CDATA[<font size="16">Nous avons donc toujours la certitude de travailler avec la plus récente version de nos documents d’équipes</font></p></div>
       <div begin="24.30s" dur="4.0"><p><![CDATA[<font size="16">indépendamment de l’auteur ou de la personne qui a modifié le contenu.</font></p></div>
      <div begin="28.75s" dur="2.50s"><p><![CDATA[<font size="16">Je ne suis pas la personne la mieux organisée. </font></p></div>
       <div begin="31.10s" dur="5.5s"><p><![CDATA[<font size="16">Auparavant, c’était toujours une vraie corvée pour moi de trouver des documents au moment où j’en avais besoin.</font></p></div>
      <div begin="36.70s" dur="3.45s"><p><![CDATA[<font size="16">Grâce à GCDOCS, il y a désormais de l’ordre dans ma vie.</font></p></div>
	  <div begin="40.20s" dur="3.25s"><p><![CDATA[<font size="16">Son système de classement est normalisé et centralisé.</font></p></div>
	  <div begin="43.40s" dur="2.20s"><p><![CDATA[<font size="16">Il est donc très simple de tout organiser.</font></p></div>
	  <div begin="45.60s" dur="5.00s"><p><![CDATA[<font size="16">Je peux facilement trouver et récupérer des documents de mon équipe quand j’en ai besoin.</font></p></div>
	  <div begin="50.70s" dur="7.00s"><p><![CDATA[<font size="16">Si jamais il y a des difficultés, je peux compter sur la fonction de recherche très puissante de GCDOCS. </font></p></div>
	  <div begin="57.00s" dur="5.45s"><p><![CDATA[<font size="16">J’aime bien le fait qu’il est possible de stocker et d’envoyer des courriels et des lourds fichiers en tant que liens.</font></p></div>
	  <div begin="62.80s" dur="5.0s"><p><![CDATA[<font size="16">Grâce à GCDOCS, il est facile de tenir tout le monde informé.</font></p></div>
	   <div begin="67.0s" dur="3.70s"><p><![CDATA[<font size="16">Nous n’avons pas à envoyer constamment de lourds fichiers</font></p></div>
	   <div begin="70.60s" dur="5.80s"><p><![CDATA[<font size="16">chaque fois que nous apportons des modifications à un document ou à une feuille de calcul.</font></p></div>
	   <div begin="76.10s" dur="2.80s"><p><![CDATA[<font size="16">Il ne s’agit pas uniquement de gagner de l’espace</font></p></div>
	   <div begin="78.75s" dur="4.00s"><p><![CDATA[<font size="16">mais également de gagner du temps et d’éviter toute éventuelle confusion.</font></p></div>
	   <div begin="83.0s" dur="1.60s"><p><![CDATA[<font size="16">Le grand intérêt de GCDOCS,</font></p></div>
	   <div begin="84.65s" dur="5.50s"><p><![CDATA[<font size="16">c’est qu’il me donne un espace public où je peux stocker les documents que je dois partager avec mes collègues</font></p></div>
	   <div begin="89.20s" dur="4.0s"><p><![CDATA[<font size="16">et autres personnes du Ministère, qui doivent y avoir accès.</font></p></div>
	    <div begin="92.30s" dur="4.0s"><p><![CDATA[<font size="16">GCDOCS me permet également de créer des signets pour mes fichiers importants</font></p></div>
		 <div begin="96.0" dur="1.0s"><p><![CDATA[<font size="16">mes favoris </font></p></div>
		 <div begin="97.0" dur="2.75s"><p><![CDATA[<font size="16">pour que je puisse y accéder rapidement quand j’en ai besoin.</font></p></div>
     
</body>
</tt>